{
  "profile": {
    "title": "손원혁 孫元爀",
    "items": [
      "1999 서울 출생"
    ]
  },
  "education": {
    "title": "학력",
    "items": [
      "2018-2020 명지전문대학 커뮤니케이션디자인과 졸업"
    ]
  },
  "soloExhibition": {
    "title": "개인전",
    "items": [
      "2022 Dream Land (CICA 미술관, 김포) 예정",
      "2021 Dream Land: Color (광명시민회관, 광명)",
      "2020 Dream Land (H art bridge, 서울)"
    ]
  },
  "groupExhibition": {
    "title": "단체전",
    "items": [
      "2021 ‘노래하는 말, 노래하는 글’ 한국타이포그라피학회전 15 (코엑스 C홀, 서울, 메타버스 온라인)",
      "2021 상대성 회로: 지속 가능성 보고서 (동덕아트갤러리, 서울)",
      "2021 Over the structures 2021 展 (CICA 미술관, 김포)",
      "2020 ‘만질 수 없는’ 한국타이포그라피학회전14 (문화역서울 284 RTO, 서울, 온라인)",
      "2019 ‘앎’ 순우리말 전시회 (명지전문대학, 서울)",
      "2019 Bauhaus mirror (DDP, Seoul)",
      "2019 The 55th Gyeonggi art contest (Gyeonggi art center gallery, Suwon)",
      "2019 Watch the world through the art (Gangnam-gu office, Seoul)",
      "2018 Miami scope art fair (Scope art fair, Miami US)",
      "2018 International young artist association contest (Gallery We, Seoul)",
      "2016 DDP Craft exposition (DDP, Seoul)",
      "2016 Rebellion of brick ‘I AM ROBOT’ (RoboPark, Bucheon)",
      "2016 Brick Convention (Hyundai Departmentstore, Pangyo)",
      "2015 Brick Convention (Hyundai Departmentstore, Pangyo)"
    ]
  },
  "prizeArchive": {
    "title": "Prize and Archive",
    "items": [
      "2021 Gwangmyeong Cultural Foundation ‘Young Artist Support Project’",
      "2019 CDAK Design award | Web·MiraeN 5th Textbook cover special award | Typeface design award",
      "2019 The 55th Gyeonggi art contest ‘Sculpture’ award",
      "2018 IYAA 1st art contest award",
      "2016 DDP Craft exposition‘Make a food using the brick’ 4th award"
    ]
  },
  "ph": {
    "title": "PH",
    "items": [
      "2019 AhnGraphics Publishers | Designer (intern)"
    ]
  },
  "division": {
    "title": "Division",
    "items": [
      "2020- E-Land Gallery ARTRO | Artist",
      "2020- Korean Society of Typography | Regular Member",
      "2019 Extypo (group) | President",
      "2019- Korean Artists Welfare Foundation | Visual Artist",
      "2018- International Young Artist Association | Plastic Artist"
    ]
  },
  "introduction": {
    "title": "Introduction",
    "items": [
      "2021 Introduction on Art Continue Nominated Artists Magazine (Art Magazine)",
      "2021 Introduction on ‘CA BOOKS’ <#254 Contactless> (Design Magazine)",
      "2020 Introduction on ‘Lego Group’s’ (Lego Official account)",
      "2017 Interview with ‘Creator’ (Korea Lego Magazine)",
      "2017 Interview with ‘The Brothers Brick’ (International Lego Media)"
    ]
  }
}